app_store_connect_mcp/__init__.py
app_store_connect_mcp/cli.py
app_store_connect_mcp/config.py
app_store_connect_mcp/server.py
app_store_connect_mcp/clients/app_store_connect.py
app_store_connect_mcp/clients/http_client.py
app_store_connect_mcp/core/base_handler.py
app_store_connect_mcp/core/constants.py
app_store_connect_mcp/core/container.py
app_store_connect_mcp/core/errors.py
app_store_connect_mcp/core/filters.py
app_store_connect_mcp/core/protocols.py
app_store_connect_mcp/core/query_builder.py
app_store_connect_mcp/core/response_handler.py
app_store_connect_mcp/domains/analytics/__init__.py
app_store_connect_mcp/domains/analytics/api_reports.py
app_store_connect_mcp/domains/analytics/api_requests.py
app_store_connect_mcp/domains/analytics/api_segments.py
app_store_connect_mcp/domains/analytics/data_downloader.py
app_store_connect_mcp/domains/analytics/handlers.py
app_store_connect_mcp/domains/app/__init__.py
app_store_connect_mcp/domains/app/handlers.py
app_store_connect_mcp/domains/testflight/__init__.py
app_store_connect_mcp/domains/testflight/handlers.py
app_store_connect_mcp/domains/users/__init__.py
app_store_connect_mcp/domains/users/api_user_invitations.py
app_store_connect_mcp/domains/users/api_users.py
app_store_connect_mcp/domains/users/handlers.py
app_store_connect_mcp/domains/xcode_cloud/__init__.py
app_store_connect_mcp/domains/xcode_cloud/api_builds.py
app_store_connect_mcp/domains/xcode_cloud/api_products.py
app_store_connect_mcp/domains/xcode_cloud/api_scm.py
app_store_connect_mcp/domains/xcode_cloud/constants.py
app_store_connect_mcp/domains/xcode_cloud/handlers.py
app_store_connect_mcp/models/__init__.py
app_store_connect_mcp/models/app_store_connect_models.py
app_store_connect_mcp/utils/__init__.py
app_store_connect_mcp/utils/parsers.py
app_store_connect_mcp-0.3.0.dist-info/licenses/LICENSE.md
app_store_connect_mcp-0.3.0.dist-info/METADATA
app_store_connect_mcp-0.3.0.dist-info/WHEEL
app_store_connect_mcp-0.3.0.dist-info/entry_points.txt
app_store_connect_mcp-0.3.0.dist-info/top_level.txt
app_store_connect_mcp-0.3.0.dist-info/RECORD
