Metadata-Version: 2.4
Name: app-store-connect-mcp
Version: 0.3.0
Summary: MCP server for interacting with Apple's App Store Connect API
Classifier: Programming Language :: Python :: 3
Classifier: Programming Language :: Python :: 3.12
Classifier: Programming Language :: Python :: 3.13
Requires-Python: >=3.12
License-File: LICENSE.md
Requires-Dist: mcp[cli]>=1.12.4
Requires-Dist: httpx>=0.27
Requires-Dist: email-validator>=2.1.0
Requires-Dist: pyjwt>=2.10.1
Requires-Dist: cryptography>=45.0.7
Provides-Extra: env
Requires-Dist: python-dotenv>=1.0.1; extra == "env"
Provides-Extra: dev
Requires-Dist: python-dotenv>=1.0.1; extra == "dev"
Requires-Dist: datamodel-code-generator>=0.25.7; extra == "dev"
Requires-Dist: pytest>=8.3.0; extra == "dev"
Requires-Dist: pytest-asyncio>=1.1.0; extra == "dev"
Dynamic: license-file
